dungngo_mcp_sqlalchemy_server-0.3.4.dist-info/licenses/LICENSE
mcp_sqlalchemy_server/__init__.py
mcp_sqlalchemy_server/server.py
dungngo_mcp_sqlalchemy_server-0.3.4.dist-info/METADATA
dungngo_mcp_sqlalchemy_server-0.3.4.dist-info/WHEEL
dungngo_mcp_sqlalchemy_server-0.3.4.dist-info/entry_points.txt
dungngo_mcp_sqlalchemy_server-0.3.4.dist-info/top_level.txt
dungngo_mcp_sqlalchemy_server-0.3.4.dist-info/RECORD
