Metadata-Version: 2.4
Name: dungngo-mcp-sqlalchemy-server
Version: 0.3.4
Summary: A simple MCP ODBC server using FastAPI and ODBC (republished for testing)
Author-email: dungngo <test@dungngo.dev>
Requires-Python: >=3.10
License-File: LICENSE
Requires-Dist: mcp[cli]>=1.4.1
Requires-Dist: pyodbc>=5.2.0
Requires-Dist: python-dotenv>=1.0.1
Dynamic: license-file
